aindo/anonymize/__init__.py
aindo/anonymize/config.py
aindo/anonymize/pipeline.py
aindo/anonymize/version.py
aindo/anonymize/techniques/__init__.py
aindo/anonymize/techniques/base.py
aindo/anonymize/techniques/binning.py
aindo/anonymize/techniques/char_masking.py
aindo/anonymize/techniques/common.py
aindo/anonymize/techniques/data_nulling.py
aindo/anonymize/techniques/hashing.py
aindo/anonymize/techniques/identity.py
aindo/anonymize/techniques/mocking.py
aindo/anonymize/techniques/perturbation.py
aindo/anonymize/techniques/swapping.py
aindo/anonymize/techniques/top_bottom_coding.py
aindo_anonymize-1.1.3.dist-info/METADATA
aindo_anonymize-1.1.3.dist-info/WHEEL
aindo_anonymize-1.1.3.dist-info/top_level.txt
aindo_anonymize-1.1.3.dist-info/RECORD
