Metadata-Version: 2.4
Name: aindo-anonymize
Version: 1.1.3
Summary: A lightweight Python library for anonymizing and pseudonymizing tabular data.
Author-email: Aindo SpA <hello@aindo.com>
License: MIT License
Project-URL: Repository, https://github.com/aindo-com/aindo-anonymize
Project-URL: Documentation, https://docs.anonymize.aindo.com
Classifier: Development Status :: 5 - Production/Stable
Classifier: Intended Audience :: Developers
Classifier: License :: OSI Approved :: MIT License
Classifier: Operating System :: OS Independent
Classifier: Programming Language :: Python
Classifier: Programming Language :: Python :: 3
Classifier: Programming Language :: Python :: 3 :: Only
Classifier: Programming Language :: Python :: 3.10
Classifier: Programming Language :: Python :: 3.11
Classifier: Programming Language :: Python :: 3.12
Classifier: Topic :: Software Development :: Libraries :: Python Modules
Classifier: Topic :: Scientific/Engineering :: Information Analysis
Classifier: Typing :: Typed
Requires-Python: <3.13,>=3.10
Requires-Dist: numpy>=1.23
Requires-Dist: pandas<3,>=2.1.1
Requires-Dist: scikit-learn<2,>=1.5
Requires-Dist: faker>=17.0.0
Provides-Extra: test
Requires-Dist: pytest~=8.3.3; extra == "test"
Requires-Dist: scipy~=1.14.1; extra == "test"
Requires-Dist: coverage; extra == "test"
Provides-Extra: dev
Requires-Dist: pre-commit; extra == "dev"
Requires-Dist: pyright; extra == "dev"
Requires-Dist: pandas-stubs; extra == "dev"
Requires-Dist: ruff==0.11.5; extra == "dev"
Requires-Dist: gitlint==0.19.1; extra == "dev"
Requires-Dist: reuse==5.0.2; extra == "dev"
